{
    "places": [
               {
               "name": "Dumont d'Urville",
               "coord": "66°39′47″ 140°00′10″",
               "id": "97215f3a-59f7-41cd-a4a2-96d408a0e233"
               }
               ],
    "scenarios": [
                  {
                  "id": "4f057ab7-b49b-4eb4-ad90-fa5995f6465e",
                  "name": "Antarctique",
                  "place": "1"
                  }
                  ],
    "situations": [
                   {
                   "name": "Acte 1 - Scene 1 - Intro/premier contact",
                   "place": "97215f3a-59f7-41cd-a4a2-96d408a0e233",
                   "parent_scenario": "4f057ab7-b49b-4eb4-ad90-fa5995f6465e",
                   "id": "3e846fa4-37c0-40d1-98a4-726002d4583f",
                   "delay": 5
                   },
                   {
                   "name": "Acte 2 - Scene 1 - Carte/Vitesse",
                   "place": "97215f3a-59f7-41cd-a4a2-96d408a0e233",
                   "parent_scenario": "4f057ab7-b49b-4eb4-ad90-fa5995f6465e",
                   "id": "e9642c32-061b-44b1-b2fc-305bc30c67c2",
                   "delay": 5
                   },
                   {
                   "name": "Acte 3 - Scene 1 - Météo/Alertes",
                   "place": "97215f3a-59f7-41cd-a4a2-96d408a0e233",
                   "parent_scenario": "4f057ab7-b49b-4eb4-ad90-fa5995f6465e",
                   "id": "1ed2aea4-903b-4585-88b8-53f7abd7a53a",
                   "delay": 5
                   },
                   {
                   "name": "Acte 4 - Scene 1 - Autonomie",
                   "place": "97215f3a-59f7-41cd-a4a2-96d408a0e233",
                   "parent_scenario": "4f057ab7-b49b-4eb4-ad90-fa5995f6465e",
                   "id": "8fb48a0d-1bf9-48d5-ae01-8079ada687af",
                   "delay": 5
                   },
                   {
                   "name": "Acte 4 - Scene 2 - Deception",
                   "place": "97215f3a-59f7-41cd-a4a2-96d408a0e233",
                   "parent_scenario": "4f057ab7-b49b-4eb4-ad90-fa5995f6465e",
                   "id": "e7cdc0f8-916f-4ab2-aab9-85e85b2e318f",
                   "delay": 5
                   },
                   {
                   "name": "Acte 5 - Scene 1 - Infos/Détail Maps",
                   "place": "97215f3a-59f7-41cd-a4a2-96d408a0e233",
                   "parent_scenario": "4f057ab7-b49b-4eb4-ad90-fa5995f6465e",
                   "id": "b8e7521e-07bc-47aa-8cf4-725137188f74",
                   "delay": 5
                   }
                   ],
    "subsituations": [
                      {
                      "name": "Je le savais que je me ferais piéger!!!!",
                      "type": "txt",
                      "parent_id": "3e846fa4-37c0-40d1-98a4-726002d4583f",
                      "child_id": "6a0e9f89-455c-4508-addf-2cd3a36cbb09",
                      "id": "aa5af3de-7b7b-4278-8af4-22fe473a9449"
                      },
                      {
                      "name": "Je suis au milieu de ce blizzard à la con",
                      "type": "txt",
                      "parent_id": "3e846fa4-37c0-40d1-98a4-726002d4583f",
                      "child_id": "03bfe7db-b420-438c-8edf-20755422c46c",
                      "id": "a523e4fa-c243-4fbb-9e83-13d6a4597b42"
                      },
                      {
                      "name": "{{blizzard}}",
                      "type": "txt",
                      "parent_id": "3e846fa4-37c0-40d1-98a4-726002d4583f",
                      "child_id": "61bff96c-c482-4e56-99c6-c082bcbc11ec",
                      "id": "3d81304e-cce8-454d-bee8-e39b878e9a9b"
                      },
                      {
                      "name": "J’y vois rien",
                      "type": "txt",
                      "parent_id": "3e846fa4-37c0-40d1-98a4-726002d4583f",
                      "child_id": "c7381183-0e8c-4d34-9569-1650c1e6c1e6",
                      "id": "d8346f6a-b581-4171-aa2d-a48b098c93c4"
                      },
                      {
                      "name": "Je sais même plus quoi faire",
                      "type": "txt",
                      "parent_id": "3e846fa4-37c0-40d1-98a4-726002d4583f",
                      "child_id": "81c32ce4-0a3f-427b-b642-5e4546c12934",
                      "id": "ad0e81d1-2c1b-4c7b-80f4-0136eb84393d"
                      },
                      {
                      "name": "Fais demi-tour ! Mets toi à l’abri",
                      "type": "choice",
                      "parent_id": "3e846fa4-37c0-40d1-98a4-726002d4583f",
                      "child_id": "6997a51b-d121-40ef-b5c2-718dd873cd55",
                      "id": "1836dc59-0c5f-48d6-9454-2b0a7fb66c68"
                      },
                      {
                      "name": "Merci, je crois que t’es mon ange gardien",
                      "type": "txt",
                      "parent_id": "3e846fa4-37c0-40d1-98a4-726002d4583f",
                      "child_id": "eac1bf64-5197-4921-86ad-f00e69d36c34",
                      "id": "497ffc8f-41f9-4e21-9885-6b203fe9917c"
                      },
                      {
                      "name": " je savais que j'aurais dû mieux étudier la carte",
                      "type": "txt",
                      "parent_id": "e9642c32-061b-44b1-b2fc-305bc30c67c2",
                      "child_id": "120c299e-e1e7-4fbd-b718-b33beb3299d7",
                      "id": "7db33dce-a8b1-40ca-927a-341fe73c4b2e"
                      },
                      {
                      "name": "Je suis persuadé que le convoi est derrière ce glacier",
                      "type": "txt",
                      "parent_id": "e9642c32-061b-44b1-b2fc-305bc30c67c2",
                      "child_id": "0b4a3d26-2738-42cf-8db8-4ae8e5abf5d2",
                      "id": "415fe782-8628-4892-974e-20e029ed722f"
                      },
                      {
                      "name": "Mais incapable de me rappeler de quel côté on doit passer…",
                      "type": "txt",
                      "parent_id": "e9642c32-061b-44b1-b2fc-305bc30c67c2",
                      "child_id": "28a86d3b-e77e-4bf2-b76b-75458a70f402",
                      "id": "7b58068c-8c77-489a-9862-07bd7157f58c"
                      },
                      {
                      "name": "Ça a l'air un peu chaud à gauche, sois prudent et prend à droite",
                      "type": "choice",
                      "parent_id": "e9642c32-061b-44b1-b2fc-305bc30c67c2",
                      "child_id": "30e816d7-2c4e-4382-ba2b-0e00eb3e2b31",
                      "id": "145db580-a27a-490e-9f68-16dac7e00093"
                      },
                      {
                      "name": "Ok, je te fais confiance sur ce coup",
                      "type": "txt",
                      "parent_id": "e9642c32-061b-44b1-b2fc-305bc30c67c2",
                      "child_id": "c65545d9-0b29-4ef1-afe0-dcf585bf7dd8",
                      "id": "6f20ec7f-4542-40ac-93cc-aa9e49195fdf"
                      },
                      {
                      "name": "Enfin j'espère que je peux 😬",
                      "type": "txt",
                      "parent_id": "e9642c32-061b-44b1-b2fc-305bc30c67c2",
                      "child_id": "6871b0b9-a417-46a1-99d9-71505908b8ec",
                      "id": "be72e1d7-232a-4fd1-8cfc-e3a1ea63114a"
                      },
                      {
                      "name": "il y a un truc magnifique avec l'Antarctique",
                      "type": "txt",
                      "parent_id": "1ed2aea4-903b-4585-88b8-53f7abd7a53a",
                      "child_id": "c86c793a-dd81-4d8c-afb9-288aecadafd9",
                      "id": "371c45de-9bd0-474c-ba7b-9a3f142ac04e"
                      },
                      {
                      "name": "La beauté du paysage est si pure",
                      "type": "txt",
                      "parent_id": "1ed2aea4-903b-4585-88b8-53f7abd7a53a",
                      "child_id": "1e0aef8d-aeee-430f-816d-0fba8278c37f",
                      "id": "a2b43fa2-b2ef-48a9-af5e-f9701c3f7b00"
                      },
                      {
                      "name": "Tiens regarde",
                      "type": "txt",
                      "parent_id": "1ed2aea4-903b-4585-88b8-53f7abd7a53a",
                      "child_id": "4d0b03cc-13c8-4f56-8159-39b473bbaa71",
                      "id": "f6cbe529-5f9d-430d-b713-909c26650350"
                      },
                      {
                      "name": "{{photo_horizon_nuage}}",
                      "type": "txt",
                      "parent_id": "1ed2aea4-903b-4585-88b8-53f7abd7a53a",
                      "child_id": "ff6c32df-e503-42ad-9290-876f751ab795",
                      "id": "de7f914b-6f05-4d68-b2fa-93562fadfaa0"
                      },
                      {
                      "name": "Wow c'est vrai que c'est dingue !!!",
                      "type": "choice",
                      "parent_id": "1ed2aea4-903b-4585-88b8-53f7abd7a53a",
                      "child_id": "69e6805b-12fc-4ec1-8083-f9705e755729",
                      "id": "e28ea192-1b77-4c03-abd0-44cf6dedcf4d"
                      },
                      {
                      "name": "C'est vrai qu'il est plutôt imposant",
                      "type": "txt",
                      "parent_id": "1ed2aea4-903b-4585-88b8-53f7abd7a53a",
                      "child_id": "871b9e0c-cd9f-457a-91f1-bd7b3690644a",
                      "id": "d98327a9-23e9-4d93-839f-c537412e6e99"
                      },
                      {
                      "name": "Mais faut absolument j’arrive à Concordia",
                      "type": "txt",
                      "parent_id": "1ed2aea4-903b-4585-88b8-53f7abd7a53a",
                      "child_id": "9354b69f-2491-4ded-b782-bcedebc59304",
                      "id": "a0be8c7b-c02a-4443-8e8e-33b5e22dcc9e"
                      },
                      {
                      "name": "La météo va tenir tu penses ?",
                      "type": "txt",
                      "parent_id": "1ed2aea4-903b-4585-88b8-53f7abd7a53a",
                      "child_id": "8361c90b-87ba-4f15-90fc-e0c7aa294614",
                      "id": "c3a8dfcc-1798-46e6-b6c7-07bdc9825575"
                      },
                      {
                      "name": "N'y penses pas, j’ai des alertes partout, fais demi-tour",
                      "type": "choice",
                      "parent_id": "1ed2aea4-903b-4585-88b8-53f7abd7a53a",
                      "child_id": "265ac766-eb87-43e9-be05-84b2684515a4",
                      "id": "aa967e35-185f-4278-9019-bd8c2e6dfcfd"
                      },
                      {
                      "name": "Bon",
                      "type": "txt",
                      "parent_id": "1ed2aea4-903b-4585-88b8-53f7abd7a53a",
                      "child_id": "6cde251b-81c2-46fd-93da-564aa58cbedd",
                      "id": "5ae8668d-3ade-451f-bd33-db2edbb714f0"
                      },
                      {
                      "name": "Souhaite moi bonne chance",
                      "type": "txt",
                      "parent_id": "1ed2aea4-903b-4585-88b8-53f7abd7a53a",
                      "child_id": "d64eb354-85f2-4d54-b592-75075f7e5fb4",
                      "id": "349fbc43-ff09-42bd-843f-b2a19b45ebc2"
                      },
                      {
                      "name": "Il se vide de son sang !!!!",
                      "type": "txt",
                      "parent_id": "8fb48a0d-1bf9-48d5-ae01-8079ada687af",
                      "child_id": "b0374bbe-8be2-4d9b-86d6-a1cafe4dbd18",
                      "id": "10675f26-c426-4a3d-ac8d-2257465a5968"
                      },
                      {
                      "name": "L'entaille est plus grande que ma main bordel!!",
                      "type": "txt",
                      "parent_id": "8fb48a0d-1bf9-48d5-ae01-8079ada687af",
                      "child_id": "ae05c326-56f7-421e-8523-d21ea1ec11e7",
                      "id": "0c373bf9-53db-40c6-89cd-b5d03151d744"
                      },
                      {
                      "name": "Je sais pas quoi faire",
                      "type": "txt",
                      "parent_id": "8fb48a0d-1bf9-48d5-ae01-8079ada687af",
                      "child_id": "b55ac959-8094-4381-ba13-7b140e4904a4",
                      "id": "71bc5392-e378-4c9f-8d93-3f178baabbdc"
                      },
                      {
                      "name": "Aide moi, je l'emmène à l'avant poste, ou j'essaye de rejoindre la base ?!",
                      "type": "txt",
                      "parent_id": "8fb48a0d-1bf9-48d5-ae01-8079ada687af",
                      "child_id": "13483e1e-7566-4052-9c10-2976d30a8a58",
                      "id": "172f33d9-9934-45a2-9dda-c8587de2e1af"
                      },
                      {
                      "name": "T’es là ?!?!?!?!?!?!",
                      "type": "txt",
                      "parent_id": "8fb48a0d-1bf9-48d5-ae01-8079ada687af",
                      "child_id": "b87eda64-92d7-4670-9823-9a36ea50d479",
                      "id": "be4622a9-5157-48cd-ac2e-a4ec74750a61"
                      },
                      {
                      "name": "Très bien je t'attendais pas, je pars pour l’avant poste",
                      "type": "txt",
                      "parent_id": "e7cdc0f8-916f-4ab2-aab9-85e85b2e318f",
                      "child_id": "0942daf8-1165-4caf-93da-266c1490b6ba",
                      "id": "1ace6974-f3b5-40a2-b614-3e8c2924ac69"
                      },
                      {
                      "name": "Salut",
                      "type": "txt",
                      "parent_id": "e7cdc0f8-916f-4ab2-aab9-85e85b2e318f",
                      "child_id": "f12118d5-2e48-4f39-b824-c9ad41ab797f",
                      "id": "7828fe12-d482-4ca3-b218-edec652c9d17"
                      },
                      {
                      "name": "Depuis qu'on l’a retrouvée à l'avant poste, Valentine est livide",
                      "type": "txt",
                      "parent_id": "b8e7521e-07bc-47aa-8cf4-725137188f74",
                      "child_id": "8ae26a2f-9133-48c1-a3f8-d434eab9626f",
                      "id": "22bc7ef1-ed8f-4b7f-9bd9-ed0115509c1c"
                      },
                      {
                      "name": "elle nous répète qu'elle est ok pour continuer, mais je le sens pas",
                      "type": "txt",
                      "parent_id": "b8e7521e-07bc-47aa-8cf4-725137188f74",
                      "child_id": "01816a38-42c0-4f24-ae17-41b6326768b8",
                      "id": "0aee28c0-17ba-471f-a161-aef669c2405a"
                      },
                      {
                      "name": "Elle doit avoir très faim",
                      "type": "choice",
                      "parent_id": "b8e7521e-07bc-47aa-8cf4-725137188f74",
                      "child_id": "b2de24f7-8365-4c4d-9b69-102160c52acd",
                      "id": "17a61d5c-7082-48cb-97ff-1cdaabaa1258"
                      },
                      {
                      "name": "Je ne sais pas à quand remonte sa dernière ration c'est vrai…",
                      "type": "txt",
                      "parent_id": "b8e7521e-07bc-47aa-8cf4-725137188f74",
                      "child_id": "c7516735-f021-4dbf-ab39-c2daaad78838",
                      "id": "3f4b1b78-0930-4de5-9de2-d1dfb3490ca5"
                      },
                      {
                      "name": "Mais du coup, on devrait aller ou d'après toi?",
                      "type": "txt",
                      "parent_id": "b8e7521e-07bc-47aa-8cf4-725137188f74",
                      "child_id": "b1a42691-13b1-4df2-be76-3b42260d24a5",
                      "id": "8289327b-e2d0-4870-97d5-204bf95173b2"
                      },
                      {
                      "name": "Il devrait y avoir de la nourriture à l'avant poste à l’ouest. Enfin espérons…",
                      "type": "choice",
                      "parent_id": "b8e7521e-07bc-47aa-8cf4-725137188f74",
                      "child_id": "be260152-d6dd-4c50-8377-aefe2c547944",
                      "id": "2813b1bf-497a-44e7-9486-67db426bb2f5"
                      },
                      {
                      "name": "Prions pour que ce soit le cas…",
                      "type": "txt",
                      "parent_id": "b8e7521e-07bc-47aa-8cf4-725137188f74",
                      "child_id": "88746d49-cf41-455e-a398-4fb90d8bff35",
                      "id": "4faacc77-ef06-4907-9b6c-43ef3ce4349e"
                      },
                      {
                      "name": "Je te tiens au courant",
                      "type": "txt",
                      "parent_id": "b8e7521e-07bc-47aa-8cf4-725137188f74",
                      "child_id": "f3274cce-a5f6-4de3-91dc-0519ba97f4b0",
                      "id": "08d7f966-3796-4978-bfc5-0384ade1b66d"
                      }
                      ],
    "text": [
             {
             "content": "Je le savais que je me ferais piéger!!!!",
             "received": "true",
             "id": "6a0e9f89-455c-4508-addf-2cd3a36cbb09"
             },
             {
             "content": "Je suis au milieu de ce blizzard à la con",
             "received": "true",
             "id": "03bfe7db-b420-438c-8edf-20755422c46c"
             },
             {
             "content": "{{blizzard}}",
             "received": "true",
             "id": "61bff96c-c482-4e56-99c6-c082bcbc11ec"
             },
             {
             "content": "J’y vois rien",
             "received": "true",
             "id": "c7381183-0e8c-4d34-9569-1650c1e6c1e6"
             },
             {
             "content": "Je sais même plus quoi faire",
             "received": "true",
             "id": "81c32ce4-0a3f-427b-b642-5e4546c12934"
             },
             {
             "content": "Merci, je crois que t’es mon ange gardien",
             "received": "true",
             "id": "eac1bf64-5197-4921-86ad-f00e69d36c34"
             },
             {
             "content": "Je savais que j'aurais dû mieux étudier la carte",
             "received": "true",
             "id": "120c299e-e1e7-4fbd-b718-b33beb3299d7"
             },
             {
             "content": "Je suis persuadé que le convoi est derrière ce glacier",
             "received": "true",
             "id": "0b4a3d26-2738-42cf-8db8-4ae8e5abf5d2"
             },
             {
             "content": "Mais incapable de me rappeler de quel côté on doit passer…",
             "received": "true",
             "id": "28a86d3b-e77e-4bf2-b76b-75458a70f402"
             },
             {
             "content": "Ok, je te fais confiance sur ce coup",
             "received": "true",
             "id": "c65545d9-0b29-4ef1-afe0-dcf585bf7dd8"
             },
             {
             "content": "Enfin j'espère que je peux 😬",
             "received": "true",
             "id": "6871b0b9-a417-46a1-99d9-71505908b8ec"
             },
             {
             "content": "Il y a un truc magnifique avec l'Antarctique",
             "received": "true",
             "id": "c86c793a-dd81-4d8c-afb9-288aecadafd9"
             },
             {
             "content": "La beauté du paysage est si pure",
             "received": "true",
             "id": "1e0aef8d-aeee-430f-816d-0fba8278c37f"
             },
             {
             "content": "Tiens regarde",
             "received": "true",
             "id": "4d0b03cc-13c8-4f56-8159-39b473bbaa71"
             },
             {
             "content": "{{photo_horizon_nuage}}",
             "received": "true",
             "id": "ff6c32df-e503-42ad-9290-876f751ab795"
             },
             {
             "content": "C'est vrai qu'il est plutôt imposant",
             "received": "true",
             "id": "871b9e0c-cd9f-457a-91f1-bd7b3690644a"
             },
             {
             "content": "Mais faut absolument j’arrive à Concordia",
             "received": "true",
             "id": "9354b69f-2491-4ded-b782-bcedebc59304"
             },
             {
             "content": "La météo va tenir tu penses ?",
             "received": "true",
             "id": "8361c90b-87ba-4f15-90fc-e0c7aa294614"
             },
             {
             "content": "Bon",
             "received": "true",
             "id": "6cde251b-81c2-46fd-93da-564aa58cbedd"
             },
             {
             "content": "Souhaite moi bonne chance",
             "received": "true",
             "id": "d64eb354-85f2-4d54-b592-75075f7e5fb4"
             },
             {
             "content": "Il se vide de son sang !!!!",
             "received": "true",
             "id": "b0374bbe-8be2-4d9b-86d6-a1cafe4dbd18"
             },
             {
             "content": "L'entaille est plus grande que ma main bordel!!",
             "received": "true",
             "id": "ae05c326-56f7-421e-8523-d21ea1ec11e7"
             },
             {
             "content": "Je sais pas quoi faire",
             "received": "true",
             "id": "b55ac959-8094-4381-ba13-7b140e4904a4"
             },
             {
             "content": "Aide moi, je l'emmène à l'avant poste, ou j'essaye de rejoindre la base ?!",
             "received": "true",
             "id": "13483e1e-7566-4052-9c10-2976d30a8a58"
             },
             {
             "content": "T’es là ?!?!?!?!?!?!",
             "received": "true",
             "id": "b87eda64-92d7-4670-9823-9a36ea50d479"
             },
             {
             "content": "Très bien je t'attends pas, je pars pour l’avant poste",
             "received": "true",
             "id": "0942daf8-1165-4caf-93da-266c1490b6ba"
             },
             {
             "content": "Salut",
             "received": "true",
             "id": "f12118d5-2e48-4f39-b824-c9ad41ab797f"
             },
             {
             "content": "Depuis qu'on l’a retrouvée à l'avant poste, Valentine est livide",
             "received": "true",
             "id": "8ae26a2f-9133-48c1-a3f8-d434eab9626f"
             },
             {
             "content": "Elle nous répète qu'elle est ok pour continuer, mais je le sens pas",
             "received": "true",
             "id": "01816a38-42c0-4f24-ae17-41b6326768b8"
             },
             {
             "content": "Je ne sais pas à quand remonte sa dernière ration c'est vrai…",
             "received": "true",
             "id": "c7516735-f021-4dbf-ab39-c2daaad78838"
             },
             {
             "content": "Mais du coup, on devrait aller ou d'après toi?",
             "received": "true",
             "id": "b1a42691-13b1-4df2-be76-3b42260d24a5"
             },
             {
             "content": "Prions pour que ce soit le cas…",
             "received": "true",
             "id": "88746d49-cf41-455e-a398-4fb90d8bff35"
             },
             {
             "content": "Je te tiens au courant",
             "received": "true",
             "id": "f3274cce-a5f6-4de3-91dc-0519ba97f4b0"
             }
             ],
    "choice": [
               {
               "id": "6997a51b-d121-40ef-b5c2-718dd873cd55"
               },
               {
               "id": "30e816d7-2c4e-4382-ba2b-0e00eb3e2b31"
               },
               {
               "id": "69e6805b-12fc-4ec1-8083-f9705e755729"
               },
               {
               "id": "28ceec71-5ed7-4e89-a59a-f462284d89ea"
               },
               {
               "id": "265ac766-eb87-43e9-be05-84b2684515a4"
               },
               {
               "id": "b2de24f7-8365-4c4d-9b69-102160c52acd"
               },
               {
               "id": "be260152-d6dd-4c50-8377-aefe2c547944"
               }
               ],
    "answer": [
               {
               "content": "Fais demi-tour ! Mets toi à l’abri",
               "parent_id": "6997a51b-d121-40ef-b5c2-718dd873cd55",
               "id": "7b76669c-fc3c-413e-af4a-cd217fb52f40"
               },
               {
               "content": "Reste sur place en attendant que ça se calme",
               "parent_id": "6997a51b-d121-40ef-b5c2-718dd873cd55",
               "id": "03cbb12f-065b-4b1f-b002-ca025f63c1a4"
               },
               {
               "content": "Je sais pas",
               "parent_id": "6997a51b-d121-40ef-b5c2-718dd873cd55",
               "id": "329572a7-61e1-45a2-b73a-c08cd861d1fc"
               },
               {
               "content": "Ça a l'air un peu chaud à gauche, sois prudent et prend à droite",
               "parent_id": "30e816d7-2c4e-4382-ba2b-0e00eb3e2b31",
               "id": "b6c45c82-2f78-48d7-9fa3-42f7949fa1cd"
               },
               {
               "content": "C'est carrément plus court à gauche, vas y direct !",
               "parent_id": "30e816d7-2c4e-4382-ba2b-0e00eb3e2b31",
               "id": "36dc7953-2c0f-4313-9de2-8ea51a692b7a"
               },
               {
               "content": "Wow c'est vrai que c'est dingue !!!",
               "parent_id": "69e6805b-12fc-4ec1-8083-f9705e755729",
               "id": "21fade7d-3eba-4fb4-8a56-2a484736a605"
               },
               {
               "content": "Euh, je trouve surtout ce nuage flippant moi",
               "parent_id": "69e6805b-12fc-4ec1-8083-f9705e755729",
               "id": "64c26224-cf03-4f9d-bf41-5455c3c70772"
               },
               {
               "content": "C'est très blanc quand même 😐",
               "parent_id": "69e6805b-12fc-4ec1-8083-f9705e755729",
               "id": "3b186dac-c0f1-4a13-8eba-eddd137727fa"
               },
               {
               "content": "N'y penses pas, j’ai des alertes partout, fais demi-tour",
               "parent_id": "265ac766-eb87-43e9-be05-84b2684515a4",
               "id": "2d0ac8e2-a46a-421a-96ee-3b1ec1f27fae"
               },
               {
               "content": "Ça se tente, si tu presses un peu le pas",
               "parent_id": "265ac766-eb87-43e9-be05-84b2684515a4",
               "id": "ad241cc0-da64-45bc-bb56-7efe81271890"
               },
               {
               "content": "Je comprends rien aux graphes 😳",
               "parent_id": "265ac766-eb87-43e9-be05-84b2684515a4",
               "id": "40b2a067-97f8-4d07-8e05-abeb5acf7fdc"
               },
               {
               "content": "Elle doit avoir très faim",
               "parent_id": "b2de24f7-8365-4c4d-9b69-102160c52acd",
               "id": "94f477c5-6bac-45ee-9784-f890416ffad7"
               },
               {
               "content": "Fais lui confiance",
               "parent_id": "b2de24f7-8365-4c4d-9b69-102160c52acd",
               "id": "812a3fdd-867d-4646-b739-139fb7d98f54"
               },
               {
               "content": "Tu lui en as parlé directement ?",
               "parent_id": "b2de24f7-8365-4c4d-9b69-102160c52acd",
               "id": "490d3fb5-2e34-4349-a1dd-33d7fc3de3e3"
               },
               {
               "content": "Il devrait y avoir de la nourriture à l'avant poste à l’ouest. Enfin espérons…",
               "parent_id": "be260152-d6dd-4c50-8377-aefe2c547944",
               "id": "5f50040a-2439-40bf-a25c-4b95defab229"
               },
               {
               "content": "Ne pas dévier du plan initial. Tout droit vers Concordia",
               "parent_id": "be260152-d6dd-4c50-8377-aefe2c547944",
               "id": "cb361f32-02a0-48d6-9032-f69d2be261c4"
               },
               {
               "content": "Je n'en ai aucune idée…",
               "parent_id": "be260152-d6dd-4c50-8377-aefe2c547944",
               "id": "c4a2c47a-3830-4acb-97b8-ff1a66c83b02"
               }
               ],
    "media": [],
    "trigger_answer": [
                       {
                       "situation_id": "e9642c32-061b-44b1-b2fc-305bc30c67c2",
                       "answer_id": "7b76669c-fc3c-413e-af4a-cd217fb52f40",
                       "id": "3e5e1cb5-289f-498e-a99e-7deb999cabf9"
                       },
                       {
                       "situation_id": "e9642c32-061b-44b1-b2fc-305bc30c67c2",
                       "answer_id": "03cbb12f-065b-4b1f-b002-ca025f63c1a4",
                       "id": "0290122a-ba2c-4dfa-8b88-027dbcab9d64"
                       },
                       {
                       "situation_id": "e9642c32-061b-44b1-b2fc-305bc30c67c2",
                       "answer_id": "329572a7-61e1-45a2-b73a-c08cd861d1fc",
                       "id": "d826ee1b-fa54-4083-914c-252ca833b88f"
                       },
                       {
                       "situation_id": "1ed2aea4-903b-4585-88b8-53f7abd7a53a",
                       "answer_id": "b6c45c82-2f78-48d7-9fa3-42f7949fa1cd",
                       "id": "4c4add5c-db00-4f03-b585-e9582d163379"
                       },
                       {
                       "situation_id": "1ed2aea4-903b-4585-88b8-53f7abd7a53a",
                       "answer_id": "36dc7953-2c0f-4313-9de2-8ea51a692b7a",
                       "id": "9b2db071-e9e6-4ae5-b71e-024375716242"
                       },
                       {
                       "situation_id": "8fb48a0d-1bf9-48d5-ae01-8079ada687af",
                       "answer_id": "2d0ac8e2-a46a-421a-96ee-3b1ec1f27fae",
                       "id": "bed10910-7320-438e-be70-b51f33f861d1"
                       },
                       {
                       "situation_id": "8fb48a0d-1bf9-48d5-ae01-8079ada687af",
                       "answer_id": "ad241cc0-da64-45bc-bb56-7efe81271890",
                       "id": "745f43b7-e4ec-45da-8fe5-0a4db0357251"
                       },
                       {
                       "situation_id": "8fb48a0d-1bf9-48d5-ae01-8079ada687af",
                       "answer_id": "40b2a067-97f8-4d07-8e05-abeb5acf7fdc",
                       "id": "61a9c579-b585-4633-bfd6-5f579a525c25"
                       },
                       {
                       "situation_id": "e7cdc0f8-916f-4ab2-aab9-85e85b2e318f",
                       "answer_id": "2d0ac8e2-a46a-421a-96ee-3b1ec1f27fae",
                       "id": "0d7418a3-bba6-41ed-89da-6ed85a5e83f2"
                       },
                       {
                       "situation_id": "e7cdc0f8-916f-4ab2-aab9-85e85b2e318f",
                       "answer_id": "ad241cc0-da64-45bc-bb56-7efe81271890",
                       "id": "383ab215-45f0-4eaf-9c9e-3cee4602cff1"
                       },
                       {
                       "situation_id": "e7cdc0f8-916f-4ab2-aab9-85e85b2e318f",
                       "answer_id": "40b2a067-97f8-4d07-8e05-abeb5acf7fdc",
                       "id": "1defa5c4-6a41-4e5c-80e7-e34d5ba67f0b"
                       },
                       {
                       "situation_id": "b8e7521e-07bc-47aa-8cf4-725137188f74",
                       "answer_id": "2d0ac8e2-a46a-421a-96ee-3b1ec1f27fae",
                       "id": "0d18c2a1-fea8-418d-8d66-76ed3891ff10"
                       },
                       {
                       "situation_id": "b8e7521e-07bc-47aa-8cf4-725137188f74",
                       "answer_id": "ad241cc0-da64-45bc-bb56-7efe81271890",
                       "id": "3fd14421-8979-4c70-b53f-dc47c51a251c"
                       },
                       {
                       "situation_id": "b8e7521e-07bc-47aa-8cf4-725137188f74",
                       "answer_id": "40b2a067-97f8-4d07-8e05-abeb5acf7fdc",
                       "id": "ab8a605f-8ea3-4255-bdfe-9ced942bb8b7"
                       }
                       ],
    "trigger_sub_sub": [
                        {
                        "triggered_id": "a523e4fa-c243-4fbb-9e83-13d6a4597b42",
                        "trigger_id": "aa5af3de-7b7b-4278-8af4-22fe473a9449",
                        "id": "e94e63d3-6127-4a8c-b052-21e57d4dfb01"
                        },
                        {
                        "triggered_id": "3d81304e-cce8-454d-bee8-e39b878e9a9b",
                        "trigger_id": "a523e4fa-c243-4fbb-9e83-13d6a4597b42",
                        "id": "96e9bd7a-f1cf-4602-b0bd-97bf5f3f188f"
                        },
                        {
                        "triggered_id": "d8346f6a-b581-4171-aa2d-a48b098c93c4",
                        "trigger_id": "3d81304e-cce8-454d-bee8-e39b878e9a9b",
                        "id": "2dc5f321-6042-464b-9617-d134c99a8261"
                        },
                        {
                        "triggered_id": "ad0e81d1-2c1b-4c7b-80f4-0136eb84393d",
                        "trigger_id": "d8346f6a-b581-4171-aa2d-a48b098c93c4",
                        "id": "b3fbb08d-3dd7-40d1-b172-90ab56280486"
                        },
                        {
                        "triggered_id": "1836dc59-0c5f-48d6-9454-2b0a7fb66c68",
                        "trigger_id": "ad0e81d1-2c1b-4c7b-80f4-0136eb84393d",
                        "id": "412268e3-b655-44c4-8c2c-6b2f99f336b5"
                        },
                        {
                        "triggered_id": "415fe782-8628-4892-974e-20e029ed722f",
                        "trigger_id": "7db33dce-a8b1-40ca-927a-341fe73c4b2e",
                        "id": "5e85f19b-c55b-4a54-91bf-9879d1aab2c8"
                        },
                        {
                        "triggered_id": "7b58068c-8c77-489a-9862-07bd7157f58c",
                        "trigger_id": "415fe782-8628-4892-974e-20e029ed722f",
                        "id": "5dad6fac-d157-4c6e-9565-6bc37dea4cd0"
                        },
                        {
                        "triggered_id": "145db580-a27a-490e-9f68-16dac7e00093",
                        "trigger_id": "7b58068c-8c77-489a-9862-07bd7157f58c",
                        "id": "1207ffa7-1e6c-4e8d-81f9-24981f9d9718"
                        },
                        {
                        "triggered_id": "be72e1d7-232a-4fd1-8cfc-e3a1ea63114a",
                        "trigger_id": "6f20ec7f-4542-40ac-93cc-aa9e49195fdf",
                        "id": "11444b3b-d065-4a33-a9fd-bdc3b4e1879a"
                        },
                        {
                        "triggered_id": "a2b43fa2-b2ef-48a9-af5e-f9701c3f7b00",
                        "trigger_id": "371c45de-9bd0-474c-ba7b-9a3f142ac04e",
                        "id": "2cda835d-cc48-46aa-99ec-3f65333b51b4"
                        },
                        {
                        "triggered_id": "f6cbe529-5f9d-430d-b713-909c26650350",
                        "trigger_id": "a2b43fa2-b2ef-48a9-af5e-f9701c3f7b00",
                        "id": "4e3108a9-1a05-4635-89f2-559d25062248"
                        },
                        {
                        "triggered_id": "de7f914b-6f05-4d68-b2fa-93562fadfaa0",
                        "trigger_id": "f6cbe529-5f9d-430d-b713-909c26650350",
                        "id": "206a20e0-8849-46fc-8a45-a8b3ed0c4d0a"
                        },
                        {
                        "triggered_id": "e28ea192-1b77-4c03-abd0-44cf6dedcf4d",
                        "trigger_id": "de7f914b-6f05-4d68-b2fa-93562fadfaa0",
                        "id": "f7c43f60-304c-41ad-8da1-d58bacece802"
                        },
                        {
                        "triggered_id": "a0be8c7b-c02a-4443-8e8e-33b5e22dcc9e",
                        "trigger_id": "d98327a9-23e9-4d93-839f-c537412e6e99",
                        "id": "785d9e97-8a9d-45bf-b857-996bb053c7f0"
                        },
                        {
                        "triggered_id": "c3a8dfcc-1798-46e6-b6c7-07bdc9825575",
                        "trigger_id": "a0be8c7b-c02a-4443-8e8e-33b5e22dcc9e",
                        "id": "a070a854-e449-470f-b6bb-600c33dd9d9b"
                        },
                        {
                        "triggered_id": "aa967e35-185f-4278-9019-bd8c2e6dfcfd",
                        "trigger_id": "c3a8dfcc-1798-46e6-b6c7-07bdc9825575",
                        "id": "584e0f97-959f-4aab-9b53-5171f40ce97c"
                        },
                        {
                        "triggered_id": "349fbc43-ff09-42bd-843f-b2a19b45ebc2",
                        "trigger_id": "5ae8668d-3ade-451f-bd33-db2edbb714f0",
                        "id": "183cf5ef-c4e7-4b2c-8d60-1f29287990e6"
                        },
                        {
                        "triggered_id": "0c373bf9-53db-40c6-89cd-b5d03151d744",
                        "trigger_id": "10675f26-c426-4a3d-ac8d-2257465a5968",
                        "id": "16e5ef82-0d9b-43c0-8370-e855678494f1"
                        },
                        {
                        "triggered_id": "71bc5392-e378-4c9f-8d93-3f178baabbdc",
                        "trigger_id": "0c373bf9-53db-40c6-89cd-b5d03151d744",
                        "id": "f026f47c-eab9-407e-8a5e-cf0e74a3ca3b"
                        },
                        {
                        "triggered_id": "172f33d9-9934-45a2-9dda-c8587de2e1af",
                        "trigger_id": "71bc5392-e378-4c9f-8d93-3f178baabbdc",
                        "id": "791b9d7a-31c7-43e3-a87d-05440ecc45bb"
                        },
                        {
                        "triggered_id": "be4622a9-5157-48cd-ac2e-a4ec74750a61",
                        "trigger_id": "172f33d9-9934-45a2-9dda-c8587de2e1af",
                        "id": "5a095ad6-43e9-4222-8859-4069892b0f85"
                        },
                        {
                        "triggered_id": "7828fe12-d482-4ca3-b218-edec652c9d17",
                        "trigger_id": "1ace6974-f3b5-40a2-b614-3e8c2924ac69",
                        "id": "42a52e9c-d8ba-42fd-9d0c-bdb28d749d4b"
                        },
                        {
                        "triggered_id": "0aee28c0-17ba-471f-a161-aef669c2405a",
                        "trigger_id": "22bc7ef1-ed8f-4b7f-9bd9-ed0115509c1c",
                        "id": "9858c803-13e3-4b54-9550-55ba84dc6f89"
                        },
                        {
                        "triggered_id": "17a61d5c-7082-48cb-97ff-1cdaabaa1258",
                        "trigger_id": "0aee28c0-17ba-471f-a161-aef669c2405a",
                        "id": "30521ad8-7ae6-4049-ae4c-20b5bf69253d"
                        },
                        {
                        "triggered_id": "8289327b-e2d0-4870-97d5-204bf95173b2",
                        "trigger_id": "3f4b1b78-0930-4de5-9de2-d1dfb3490ca5",
                        "id": "f5224560-1171-4da7-98cf-ef9f1da78729"
                        },
                        {
                        "triggered_id": "2813b1bf-497a-44e7-9486-67db426bb2f5",
                        "trigger_id": "8289327b-e2d0-4870-97d5-204bf95173b2",
                        "id": "4c07060c-8d87-4b1f-af74-29709e3f0c22"
                        },
                        {
                        "triggered_id": "08d7f966-3796-4978-bfc5-0384ade1b66d",
                        "trigger_id": "4faacc77-ef06-4907-9b6c-43ef3ce4349e",
                        "id": "16516262-1f57-4a8d-afcf-fcb75d050fa5"
                        }
                        ],
    "trigger_sub_answer": [
                           {
                           "sub_id": "497ffc8f-41f9-4e21-9885-6b203fe9917c",
                           "answer_id": "7b76669c-fc3c-413e-af4a-cd217fb52f40",
                           "id": "0f4c3990-4c14-4c3b-b41c-d601002d9bd0"
                           },
                           {
                           "sub_id": "497ffc8f-41f9-4e21-9885-6b203fe9917c",
                           "answer_id": "03cbb12f-065b-4b1f-b002-ca025f63c1a4",
                           "id": "3cc67a43-7651-4aac-a9ff-e8c0ba40a253"
                           },
                           {
                           "sub_id": "497ffc8f-41f9-4e21-9885-6b203fe9917c",
                           "answer_id": "329572a7-61e1-45a2-b73a-c08cd861d1fc",
                           "id": "ea00a86e-596d-4537-a9f1-476e598be1e3"
                           },
                           {
                           "sub_id": "6f20ec7f-4542-40ac-93cc-aa9e49195fdf",
                           "answer_id": "b6c45c82-2f78-48d7-9fa3-42f7949fa1cd",
                           "id": "597e88d4-4883-4bfb-b29a-9c6b18475287"
                           },
                           {
                           "sub_id": "6f20ec7f-4542-40ac-93cc-aa9e49195fdf",
                           "answer_id": "36dc7953-2c0f-4313-9de2-8ea51a692b7a",
                           "id": "31c98da0-88d5-4af0-befc-7c259ab119c5"
                           },
                           {
                           "sub_id": "d98327a9-23e9-4d93-839f-c537412e6e99",
                           "answer_id": "21fade7d-3eba-4fb4-8a56-2a484736a605",
                           "id": "96d29bd8-71a7-4622-98ba-578a33c94045"
                           },
                           {
                           "sub_id": "d98327a9-23e9-4d93-839f-c537412e6e99",
                           "answer_id": "64c26224-cf03-4f9d-bf41-5455c3c70772",
                           "id": "b1f7d037-5875-4412-b04e-3370ced0cf26"
                           },
                           {
                           "sub_id": "d98327a9-23e9-4d93-839f-c537412e6e99",
                           "answer_id": "3b186dac-c0f1-4a13-8eba-eddd137727fa",
                           "id": "34b6d380-dd5e-433f-a4e6-fc067f835b19"
                           },
                           {
                           "sub_id": "5ae8668d-3ade-451f-bd33-db2edbb714f0",
                           "answer_id": "2d0ac8e2-a46a-421a-96ee-3b1ec1f27fae",
                           "id": "1411f94a-d2e6-4e4c-8d5f-31df88a9691e"
                           },
                           {
                           "sub_id": "5ae8668d-3ade-451f-bd33-db2edbb714f0",
                           "answer_id": "ad241cc0-da64-45bc-bb56-7efe81271890",
                           "id": "4fbe3ce7-c582-42fa-81c3-4e8f26209e89"
                           },
                           {
                           "sub_id": "5ae8668d-3ade-451f-bd33-db2edbb714f0",
                           "answer_id": "40b2a067-97f8-4d07-8e05-abeb5acf7fdc",
                           "id": "f759e607-4f68-44f8-bac2-0b549c5bb123"
                           },
                           {
                           "sub_id": "3f4b1b78-0930-4de5-9de2-d1dfb3490ca5",
                           "answer_id": "94f477c5-6bac-45ee-9784-f890416ffad7",
                           "id": "c2286db9-d70f-48d3-a9d6-a75463df6479"
                           },
                           {
                           "sub_id": "3f4b1b78-0930-4de5-9de2-d1dfb3490ca5",
                           "answer_id": "812a3fdd-867d-4646-b739-139fb7d98f54",
                           "id": "b89c23cd-98c5-47b9-9799-7ef223f65759"
                           },
                           {
                           "sub_id": "3f4b1b78-0930-4de5-9de2-d1dfb3490ca5",
                           "answer_id": "490d3fb5-2e34-4349-a1dd-33d7fc3de3e3",
                           "id": "e433513b-13b1-48c0-9cff-cea1a26f1245"
                           },
                           {
                           "sub_id": "4faacc77-ef06-4907-9b6c-43ef3ce4349e",
                           "answer_id": "5f50040a-2439-40bf-a25c-4b95defab229",
                           "id": "d6d97056-5ba2-4d24-86de-ad6113e22fae"
                           },
                           {
                           "sub_id": "4faacc77-ef06-4907-9b6c-43ef3ce4349e",
                           "answer_id": "cb361f32-02a0-48d6-9032-f69d2be261c4",
                           "id": "f20c0b6e-d854-4d1f-a9ea-2eb447b1ee5c"
                           },
                           {
                           "sub_id": "4faacc77-ef06-4907-9b6c-43ef3ce4349e",
                           "answer_id": "c4a2c47a-3830-4acb-97b8-ff1a66c83b02",
                           "id": "f03ad115-d3d5-4c7f-8329-24d661c58fab"
                           }
                           ]
}